safetydance/__init__.py
safetydance/_safetydance.py
safetydance/extensions.py
safetydance/file_util.py
safetydance/jupyter.py
safetydance-0.3.2.dist-info/LICENSE.txt
safetydance-0.3.2.dist-info/WHEEL
safetydance-0.3.2.dist-info/METADATA
safetydance-0.3.2.dist-info/RECORD
