Metadata-Version: 2.1
Name: safetydance
Version: 0.3.2
Summary: A typesafe system for defining and composing steps.
Home-page: https://github.com/dcharbon/safetydance
License: MIT
Author: David Charboneau
Author-email: david@adadabase.com
Requires-Python: >=3.7,<4.0
Classifier: License :: OSI Approved :: MIT License
Classifier: Programming Language :: Python :: 3
Classifier: Programming Language :: Python :: 3.10
Classifier: Programming Language :: Python :: 3.7
Classifier: Programming Language :: Python :: 3.8
Classifier: Programming Language :: Python :: 3.9
Project-URL: Repository, https://github.com/dcharbon/safetydance.git
